elke27_lib/__init__.py
elke27_lib/client.py
elke27_lib/const.py
elke27_lib/discovery.py
elke27_lib/dispatcher.py
elke27_lib/encryption.py
elke27_lib/errors.py
elke27_lib/events.py
elke27_lib/framing.py
elke27_lib/hello.py
elke27_lib/kernel.py
elke27_lib/linking.py
elke27_lib/message.py
elke27_lib/outbound.py
elke27_lib/pending.py
elke27_lib/permissions.py
elke27_lib/presentation.py
elke27_lib/provisioning.py
elke27_lib/redact.py
elke27_lib/session.py
elke27_lib/states.py
elke27_lib/types.py
elke27_lib/util.py
elke27_lib/features/area.py
elke27_lib/features/bus_ios.py
elke27_lib/features/control.py
elke27_lib/features/keypad.py
elke27_lib/features/log.py
elke27_lib/features/network_param.py
elke27_lib/features/output.py
elke27_lib/features/rule.py
elke27_lib/features/system.py
elke27_lib/features/tstat.py
elke27_lib/features/user.py
elke27_lib/features/zone.py
elke27_lib/generators/__init__.py
elke27_lib/generators/all_generators.py
elke27_lib/generators/area.py
elke27_lib/generators/bus_ios.py
elke27_lib/generators/control.py
elke27_lib/generators/keypad.py
elke27_lib/generators/log.py
elke27_lib/generators/network_param.py
elke27_lib/generators/output.py
elke27_lib/generators/registry.py
elke27_lib/generators/rule.py
elke27_lib/generators/system.py
elke27_lib/generators/tstat.py
elke27_lib/generators/user.py
elke27_lib/generators/zone.py
elke27_lib/handlers/all_handlers.py
elke27_lib/handlers/area.py
elke27_lib/handlers/bus_ios.py
elke27_lib/handlers/control.py
elke27_lib/handlers/keypad.py
elke27_lib/handlers/log.py
elke27_lib/handlers/network_param.py
elke27_lib/handlers/output.py
elke27_lib/handlers/rule.py
elke27_lib/handlers/system.py
elke27_lib/handlers/tstat.py
elke27_lib/handlers/user.py
elke27_lib/handlers/zone.py
elke27-0.1.2.dist-info/METADATA
elke27-0.1.2.dist-info/WHEEL
elke27-0.1.2.dist-info/entry_points.txt
elke27-0.1.2.dist-info/licenses/LICENSE
elke27-0.1.2.dist-info/RECORD
