Metadata-Version: 2.4
Name: elke27
Version: 0.1.2
Summary: Library for interfacing with the Elk Products E27 Alarm Engine
Project-URL: Repository, https://github.com/mitchmitchell/elke27
Author-email: mitchmitchell <mitchmitchell1616@msn.com>
License-Expression: MIT
License-File: LICENSE
Classifier: Development Status :: 4 - Beta
Classifier: Intended Audience :: Developers
Classifier: Operating System :: OS Independent
Classifier: Programming Language :: Python
Classifier: Programming Language :: Python :: 3
Classifier: Programming Language :: Python :: 3.11
Classifier: Programming Language :: Python :: 3.12
Classifier: Programming Language :: Python :: 3.13
Classifier: Programming Language :: Python :: 3.14
Classifier: Typing :: Typed
Requires-Python: <4.0,>=3.11
Requires-Dist: cryptography>=42.0.0
Requires-Dist: typing-extensions>=4.9.0
